mixturemapping/__init__.py
mixturemapping/binning.py
mixturemapping/distributions.py
mixturemapping/utils.py
mixturemapping/layers/__init__.py
mixturemapping/layers/_mapping.py
mixturemapping/layers/binyield.py
mixturemapping/layers/covmatrix.py
mixturemapping/layers/distribution.py
mixturemapping/layers/disttrafo.py
mixturemapping/layers/generalmapping.py
mixturemapping/layers/gmrmapping.py
mixturemapping/layers/linearmapping.py
mixturemapping/layers/normalization.py
mixturemapping-0.5.5.dist-info/METADATA
mixturemapping-0.5.5.dist-info/WHEEL
mixturemapping-0.5.5.dist-info/top_level.txt
mixturemapping-0.5.5.dist-info/RECORD
