Metadata-Version: 2.1
Name: mixturemapping
Version: 0.5.5
Home-page: https://vk.github.io/mixturemapping-doc/
Keywords: tensorflow distributions gaussian mixtures
Classifier: Operating System :: OS Independent
Classifier: Programming Language :: Python
Classifier: Programming Language :: Python :: 3.7
Classifier: Programming Language :: Python :: 3.8
Classifier: Programming Language :: Python :: 3.9
Classifier: Programming Language :: Python :: 3.10
Classifier: Programming Language :: Python :: 3 :: Only
Requires-Python: >=3.7
